Metadata-Version: 2.1
Name: torch-cv
Version: 0.1.1
Summary: A high level package for Computer Vision with pytorch
Home-page: https://github.com/RJaikanth/torch-cv
Author: Raghhuveer Jaikanth
Author-email: raghhuveerj97@gmail.com
License: UNKNOWN
Platform: UNKNOWN
Classifier: Programming Language :: Python :: 3.8
Classifier: License :: OSI Approved :: MIT License
Classifier: Development Status :: 4 - Beta
Classifier: Natural Language :: English
Classifier: Operating System :: Unix
Requires-Python: >=3.7
